cli/__init__.py
cli/main.py
cli/commands/__init__.py
cli/commands/template/__init__.py
cli/commands/template/list.py
cli/commands/workshop/__init__.py
cli/commands/workshop/create.py
cli/config/__init__.py
cli/config/config.py
gashokoru_cli-0.2.0.dist-info/METADATA
gashokoru_cli-0.2.0.dist-info/WHEEL
gashokoru_cli-0.2.0.dist-info/entry_points.txt
gashokoru_cli-0.2.0.dist-info/top_level.txt
gashokoru_cli-0.2.0.dist-info/RECORD
